saiph/__init__.py
saiph/conftest.py
saiph/contribution.py
saiph/contribution_test.py
saiph/exception.py
saiph/inverse_transform.py
saiph/inverse_transform_test.py
saiph/models.py
saiph/projection.py
saiph/projection_test.py
saiph/py.typed
saiph/serializer.py
saiph/serializer_test.py
saiph/visualization.py
saiph/lib/size.py
saiph/reduction/__init__.py
saiph/reduction/famd.py
saiph/reduction/famd_sparse.py
saiph/reduction/famd_sparse_test.py
saiph/reduction/famd_test.py
saiph/reduction/mca.py
saiph/reduction/mca_test.py
saiph/reduction/pca.py
saiph/reduction/pca_test.py
saiph/reduction/utils/__init__.py
saiph/reduction/utils/common.py
saiph/reduction/utils/common_test.py
saiph/reduction/utils/svd.py
saiph/reduction/utils/svd_test.py
saiph/tests/__init_.py
saiph/tests/benchmark_test.py
saiph/tests/profile_cpu.py
saiph/tests/profile_memory.py
saiph-2.0.5.dist-info/METADATA
saiph-2.0.5.dist-info/WHEEL
saiph-2.0.5.dist-info/licenses/LICENSE
saiph-2.0.5.dist-info/RECORD
